PyCrystallography/PyAnimate.py
PyCrystallography/PyCrystallography.py
PyCrystallography/PyPacking.py
PyCrystallography/PyShapes.py
PyCrystallography/__init__.py
PyCrystallography/animate.py
PyCrystallography/geometry.py
PyCrystallography/lattice.py
PyCrystallography/main.py
PyCrystallography/miller_indices.py
PyCrystallography/moire.py
PyCrystallography/operations.py
PyCrystallography/packing.py
PyCrystallography/stereographic_projection.py
PyCrystallography/structure.py
PyCrystallography/test.py
PyCrystallography/unit_cell.py
PyCrystallography/xray_diffraction.py
PyCrystallography-0.2.1.dist-info/DESCRIPTION.rst
PyCrystallography-0.2.1.dist-info/METADATA
PyCrystallography-0.2.1.dist-info/RECORD
PyCrystallography-0.2.1.dist-info/WHEEL
PyCrystallography-0.2.1.dist-info/metadata.json
PyCrystallography-0.2.1.dist-info/top_level.txt
