Metadata-Version: 2.0
Name: PyCrystallography
Version: 0.2.1
Summary: Python 3 package being written to illustrate crystallography
Home-page: https://github.com/Shellywell123/PyCrystallography
Author: Shellywell123
License: UNKNOWN
Platform: UNKNOWN
Classifier: Programming Language :: Python :: 3
Classifier: License :: OSI Approved :: MIT License
Classifier: License :: OSI Approved :: GNU General Public License v3 (GPLv3)
Requires-Python: >=3.6
Requires-Dist: matplotlib (>=3.3.2)
Requires-Dist: numpy (>=1.19.2)
Requires-Dist: imageio (>=2.9.0)
